create_jira_issue/__init__.py
create_jira_issue/create_jira_issue.py
create_jira_issue-0.1.6.dist-info/entry_points.txt
create_jira_issue-0.1.6.dist-info/LICENSE.txt
create_jira_issue-0.1.6.dist-info/WHEEL
create_jira_issue-0.1.6.dist-info/METADATA
create_jira_issue-0.1.6.dist-info/RECORD
